flask_logging_decorator/__init__.py
flask_logging_decorator-0.0.5.dist-info/METADATA
flask_logging_decorator-0.0.5.dist-info/RECORD
flask_logging_decorator-0.0.5.dist-info/WHEEL
flask_logging_decorator-0.0.5.dist-info/top_level.txt
