Metadata-Version: 2.1
Name: flask-logging-decorator
Version: 0.0.5
Summary: Simple logging decorator for Flask.
Home-page: https://github.com/sgykfjsm/flask-logging-decorator
Author: Shigeyuki Fujishima
Author-email: shigeyuki.fujishima@gmail.com
License: UNKNOWN
Keywords: flask logging decorator
Platform: UNKNOWN
Classifier: License :: OSI Approved :: MIT License
Classifier: Programming Language :: Python :: 3.6
Requires-Python: >=3.5, !=2.*.*, !=3.0.*, !=3.1.*, !=3.2.*, !=3.3.*
